orange3_factoranalysis-0.0.3.dist-info/licenses/LICENSE
orangecontrib/__init__.py
orangecontrib/factoranalysis/__init__.py
orangecontrib/factoranalysis/widgets/__init__.py
orangecontrib/factoranalysis/widgets/darkmode.py
orangecontrib/factoranalysis/widgets/owfactoranalysis.py
orangecontrib/factoranalysis/widgets/owfactoranalysis_viewer.py
orangecontrib/factoranalysis/widgets/icons/factor-analysis-viewer.svg
orangecontrib/factoranalysis/widgets/icons/factor-analysis.svg
tests/test_factoranalysis.py
orange3_factoranalysis-0.0.3.dist-info/METADATA
orange3_factoranalysis-0.0.3.dist-info/WHEEL
orange3_factoranalysis-0.0.3.dist-info/entry_points.txt
orange3_factoranalysis-0.0.3.dist-info/top_level.txt
orange3_factoranalysis-0.0.3.dist-info/RECORD
