Metadata-Version: 2.4
Name: orange3-factoranalysis
Version: 0.0.3
Summary: Orange3 add-on for Factor Analysis visualization
Author-email: Chris Lee <github@chrislee.dhs.org>
License: CC-BY-NC-SA-4.0
Project-URL: Homepage, https://github.com/chrislee35/orange3-factoranalysis
Keywords: orange3 add-on
Classifier: Development Status :: 3 - Alpha
Classifier: Intended Audience :: Education
Classifier: Intended Audience :: Science/Research
Classifier: Programming Language :: Python :: 3 :: Only
Requires-Python: >=3.11
License-File: LICENSE
Requires-Dist: Orange3>=3.34.0
Requires-Dist: orange-canvas-core>=0.1.28
Requires-Dist: orange-widget-base>=4.20.0
Requires-Dist: scipy>=1.13.1
Requires-Dist: pandas>=2.2.3
Requires-Dist: factor_analyzer>=0.5.1
Requires-Dist: PyQtWebEngine>=5.15.7
Provides-Extra: test
Requires-Dist: coverage; extra == "test"
Provides-Extra: doc
Requires-Dist: sphinx; extra == "doc"
Requires-Dist: recommonmark; extra == "doc"
Requires-Dist: sphinx_rtd_theme; extra == "doc"
Dynamic: license-file
